LICENSE
README.md
setup.py
tkcap/__init__.py
tkcap/exceptions.py
tkcap.egg-info/PKG-INFO
tkcap.egg-info/SOURCES.txt
tkcap.egg-info/dependency_links.txt
tkcap.egg-info/requires.txt
tkcap.egg-info/top_level.txt