Metadata-Version: 2.1
Name: tkcap
Version: 0.0.4
Summary: Grabs screenshot of a tkinter window
Home-page: https://github.com/ghanteyyy/tkcap.git
Author: ghanteyyy
Author-email: ghanteyyy@gmail.com
License: MIT
Classifier: Programming Language :: Python :: 3
Classifier: License :: OSI Approved :: MIT License
Classifier: Operating System :: OS Independent
Requires-Python: >=3
License-File: LICENSE
